py_guide/__init__.py
py_guide/__main__.py
py_guide/console_menu.py
py_guide/get_pip.py
py_guide/log_4_trees.py
py_guide/logging_trees.py
py_guide/project_factory.py
py_guide/py_template/.gitignore
py_guide/py_template/LICENSE-MIT
py_guide/py_template/README.rst
py_guide/py_template/__init__.py
py_guide/py_template/__main__.py
py_guide/py_template/dist_pypi.bat
py_guide/py_template/dist_pypi_config.default
py_guide/py_template/jrepl.bat
py_guide/py_template/project.cfg
py_guide/py_template/requirements.txt
py_guide/py_template/setup.py
py_guide/py_template/.idea/runConfigurations/Build_Sphinx_docs.xml
py_guide/py_template/.idea/runConfigurations/Build_setup_wheel.xml
py_guide/py_template/docs_source/__init__.py
py_guide/py_template/docs_source/conf.py
py_guide/py_template/docs_source/index.rst
py_guide/py_template/docs_source/next_steps.rst
py_guide/py_template/docs_source/readme.rst
py_guide/py_template/src/__init__.py
py_guide/py_template/src/__main__.py
py_guide/py_template/src/console_menu.py
py_guide/py_template/src/logging_trees.py
sjb.pyguide-0.2.5.dist-info/LICENSE
sjb.pyguide-0.2.5.dist-info/METADATA
sjb.pyguide-0.2.5.dist-info/WHEEL
sjb.pyguide-0.2.5.dist-info/entry_points.txt
sjb.pyguide-0.2.5.dist-info/top_level.txt
sjb.pyguide-0.2.5.dist-info/RECORD
