Metadata-Version: 2.1
Name: sjb.pyguide
Version: 0.2.5
Summary: Python Project & Coding Standards for Practicing Wizards
Home-page: https://github.com/shawnjburke/py_guide
Author: Shawn J Burke
Author-email: pypi.python@teamburke.com
License: GNU GENERAL PUBLIC LICENSE
Project-URL: Bug Tracker, https://github.com/shawnjburke/py_guide/issues/
Project-URL: Documentation, https://shawnjburke.github.io/py_guide/
Project-URL: Source Code, https://github.com/shawnjburke/py_guide/
Platform: UNKNOWN
Classifier: Development Status :: 4 - Beta
Classifier: Intended Audience :: Developers
Classifier: License :: OSI Approved :: MIT License
Classifier: Natural Language :: English
Classifier: Operating System :: OS Independent
Classifier: Programming Language :: Python
Classifier: Programming Language :: Python :: 2.7
Classifier: Programming Language :: Python :: 3
Classifier: Programming Language :: Python :: 3.3
Classifier: Programming Language :: Python :: 3.4
Classifier: Programming Language :: Python :: 3.5
Classifier: Programming Language :: Python :: 3.6
Classifier: Programming Language :: Python :: Implementation :: CPython
Classifier: Topic :: Software Development :: Quality Assurance
Classifier: Topic :: Software Development :: Testing
Requires-Dist: configparser2 (==4.0.0)
Requires-Dist: Menu (==3.1.0)
Requires-Dist: Jinja2 (==2.10.1)
Requires-Dist: requests
Requires-Dist: twine (==1.13.0)
